{
  "required": true,
  "minVersion": "0.8",
  "package": "marsh.town.brb.mixins",
  "compatibilityLevel": "JAVA_16",
  "client": [
    "BrewingStandScreenMixin",
    "DisableBook",
    "DisableBounce",
    "MouseScrollHandler",
    "RemoveBookButton",
    "RemoveToasts",
    "SmithingScreenMixin",
    "accessors.HolderReferenceAccessor",
    "accessors.InventoryAccessor",
    "accessors.OverlayRecipeButtonAccessor",
    "accessors.OverlayRecipeComponentAccessor",
    "accessors.RecipeBookComponentAccessor",
    "accessors.RecipeBookPageAccessor",
    "accessors.SmithingTransformRecipeAccessor",
    "accessors.SmithingTrimRecipeAccessor",
    "alternativerecipes.OverlayRecipeButtonMixin",
    "centered.RecipeBookComponentMixin",
    "instantcraft.ClientPacketListenerMixin",
    "instantcraft.MultiPlayerGameModeMixin",
    "instantcraft.RecipeBookComponentMixin",
    "instantcraft.RecipeButtonMixin",
    "pins.AbstractContainerScreenMixin",
    "pins.RecipeBookComponentMixin",
    "pins.RecipeBookPageMixin",
    "pins.RecipeButtonMixin",
    "scrollablepages.RecipeBookPageMixin",
    "settings.RecipeBookComponentMixin",
    "ungroup.ClientRecipeBookMixin",
    "ungroup.RecipeBookComponentMixin",
    "unlockrecipes.ClientPacketListenerMixin",
    "unlockrecipes.MultiPlayerGameModeMixin"
  ],
  "injectors": {
    "defaultRequire": 1
  }
}
